proto_matcher/__init__.py
proto_matcher/compare/__init__.py
proto_matcher/compare/compare.py
proto_matcher/compare/compare_test.py
proto_matcher/compare/iter_util.py
proto_matcher/matcher/__init__.py
proto_matcher/matcher/matcher.py
proto_matcher/matcher/matcher_test.py
hamcrest_proto-0.0.6.dist-info/LICENSE
hamcrest_proto-0.0.6.dist-info/METADATA
hamcrest_proto-0.0.6.dist-info/WHEEL
hamcrest_proto-0.0.6.dist-info/top_level.txt
hamcrest_proto-0.0.6.dist-info/RECORD
