Metadata-Version: 2.2
Name: hamcrest_proto
Version: 0.0.6
Summary: Hamcrest matchers for protobufs
Home-page: https://github.com/mdepinet/hamcrest-proto
Author: mdepinet
Author-email: 
Classifier: Programming Language :: Python :: 3
Classifier: License :: OSI Approved :: Apache Software License
Classifier: Operating System :: OS Independent
Requires-Python: >=3.7
License-File: LICENSE
Dynamic: author
Dynamic: classifier
Dynamic: description
Dynamic: description-content-type
Dynamic: home-page
Dynamic: requires-python
Dynamic: summary
